backlog/__init__.py
backlog/__main__.py
backlog/api.py
backlog/cli.py
backlog-2.0.4.dist-info/LICENSE
backlog-2.0.4.dist-info/METADATA
backlog-2.0.4.dist-info/WHEEL
backlog-2.0.4.dist-info/entry_points.txt
backlog-2.0.4.dist-info/top_level.txt
backlog-2.0.4.dist-info/RECORD
