Metadata-Version: 2.1
Name: backlog
Version: 2.0.4
Summary: A Glorified TODO list
Home-page: https://pypi.org/project/backlog
Author: David Tucker
Author-email: david@tucker.name
License: LGPLv2+
Project-URL: Code, https://github.com/dmtucker/backlog
Project-URL: Documentation, https://dmtucker.github.io/backlog
Project-URL: Issues, https://github.com/dmtucker/backlog/issues
Keywords: notes backlog todo list
Platform: UNKNOWN
Classifier: License :: OSI Approved :: GNU Lesser General Public License v2 or later (LGPLv2+)
Classifier: Intended Audience :: End Users/Desktop
Classifier: Programming Language :: Python :: 3.7
Classifier: Programming Language :: Python :: 3.8
Classifier: Development Status :: 5 - Production/Stable
Requires-Python: >= 3.7
Requires-Dist: click (>=7.1)
Requires-Dist: setuptools (>=46.1)
